nma/__init__.py
nma/__main__.py
nma/exclamation-mark.png
nma/hourglass.png
nma/main.py
nma/notify_decorator.py
nma/send_notification.py
nma-0.1.data/scripts/nma
nma-0.1.dist-info/LICENSE
nma-0.1.dist-info/METADATA
nma-0.1.dist-info/WHEEL
nma-0.1.dist-info/top_level.txt
nma-0.1.dist-info/RECORD
