Metadata-Version: 2.1
Name: nma
Version: 0.1
Summary: Sends a desktop notification when a process finishes
Home-page: https://github.com/jrodal98/nma
Author: Jacob Rodal
Author-email: jr6ff@virginia.edu
License: UNKNOWN
Download-URL: https://github.com/jrodal98/nma/archive/v0.1.tar.gz
Platform: UNKNOWN
Classifier: Programming Language :: Python :: 3
Classifier: License :: OSI Approved :: MIT License
Classifier: Operating System :: POSIX :: Linux
Classifier: Operating System :: MacOS
Requires-Python: >=3.6
